{"po": "KS", "name": "Kansas", "state_dpi": 42.17, "nat_pvi_anchor": 50.76, "fips2name": {"103": "Leavenworth County", "201": "Washington County", "063": "Gove County", "083": "Hodgeman County", "065": "Graham County", "021": "Cherokee County", "163": "Rooks County", "105": "Lincoln County", "193": "Thomas County", "029": "Cloud County", "161": "Riley County", "119": "Meade County", "055": "Finney County", "087": "Jefferson County", "005": "Atchison County", "057": "Ford County", "147": "Phillips County", "135": "Ness County", "133": "Neosho County", "035": "Cowley County", "093": "Kearny County", "079": "Harvey County", "109": "Logan County", "039": "Decatur County", "195": "Trego County", "197": "Wabaunsee County", "059": "Franklin County", "191": "Sumner County", "185": "Stafford County", "125": "Montgomery County", "207": "Woodson County", "089": "Jewell County", "073": "Greenwood County", "111": "Lyon County", "115": "Marion County", "123": "Mitchell County", "075": "Hamilton County", "041": "Dickinson County", "095": "Kingman County", "001": "Allen County", "203": "Wichita County", "177": "Shawnee County", "037": "Crawford County", "205": "Wilson County", "011": "Bourbon County", "121": "Miami County", "149": "Pottawatomie County", "159": "Rice County", "027": "Clay County", "019": "Chautauqua County", "049": "Elk County", "139": "Osage County", "113": "McPherson County", "137": "Norton County", "003": "Anderson County", "071": "Greeley County", "017": "Chase County", "077": "Harper County", "031": "Coffey County", "131": "Nemaha County", "171": "Scott County", "153": "Rawlins County", "091": "Johnson County", "099": "Labette County", "127": "Morris County", "173": "Sedgwick County", "107": "Linn County", "145": "Pawnee County", "155": "Reno County", "081": "Haskell County", "043": "Doniphan County", "023": "Cheyenne County", "143": "Ottawa County", "015": "Butler County", "101": "Lane County", "129": "Morton County", "033": "Comanche County", "165": "Rush County", "157": "Republic County", "067": "Grant County", "179": "Sheridan County", "117": "Marshall County", "209": "Wyandotte County", "183": "Smith County", "061": "Geary County", "181": "Sherman County", "025": "Clark County", "151": "Pratt County", "175": "Seward County", "047": "Edwards County", "045": "Douglas County", "007": "Barber County", "199": "Wallace County", "069": "Gray County", "097": "Kiowa County", "053": "Ellsworth County", "189": "Stevens County", "169": "Saline County", "187": "Stanton County", "013": "Brown County", "051": "Ellis County", "141": "Osborne County", "009": "Barton County", "167": "Russell County", "085": "Jackson County"}, "levels": [{"id": "county", "label": "County"}, {"id": "school", "label": "School district"}, {"id": "house", "label": "State House"}, {"id": "senate", "label": "State Senate"}, {"id": "cd", "label": "Congress"}, {"id": "cousub", "label": "Township"}], "subs": [], "bounds": [[-102.051744, 36.993016], [-94.588658, 40.003078]], "state": {"dpi": 42.17, "dpi_pres": 40.8, "dpi_mid": 43.4, "elasticity": 1.0, "trend_per_cycle": -0.71, "pres_trend": -0.71, "mid_trend": null, "lt_pres_trend": 1.22, "dispersion": 4.65, "n_races": 11, "ci95": 2.75, "pres_avg": 42.15, "vs_state": 0.0, "pvi_vs_state": -0.02, "pvi_vs_nation": -8.61, "exact_county_share": 1.0, "confidence": 100, "ballots_mid": 999702, "ballots_pres": 1287367, "reg_current": 1803989, "win_m": 499852, "win_p": 643684, "n_counties": 105, "n_house": 125, "n_senate": 40, "house_tossups": 14, "senate_tossups": 2}}